[{"type":"vehicle","id":"8319023","attributes":{"agent_coords_0_coord":-25.895796,"agent_coords_1_coord":28.16751,"agent_featured":"2","agent_locality":"Centurion","agent_name":"WeBuyCars Midstream","agent_vin_required":"2","body_type":"Hatchback","body_type_code":"H/B","colour":"Black","commercial_type":"a","condition":"Below Average","description":"2015 Peugeot 208 1.6 VTI Allure 5-Door","finance_available":"1","fuel_type":"Petrol","image":{"version":1835949931,"count":7,"path":"carsimages","name":"8319023","extension":".jpg"},"make":"Peugeot","mileage":"130 000 Km","model":"208","new_or_used":"Used","options":"","price":81900,"province":"Gauteng","reference":"DD0D12222","roadworthy":"1","search_type":"A","seller_type":"agent","title":"2015 Peugeot 208 1.6 VTi Allure 5-dr","transmission":"Manual","variant":"1.6 VTi Allure 5-dr","variant_short":"1.6","vehicle_axle_config":"4X2","website_url":"https://www.cars.co.za/for-sale/used/2015-Peugeot-208-1.6-VTi-Allure-5-dr-Gauteng-Centurion/8319023/","year":2015},"relationships":{"seller":{"data":{"type":"seller","id":"3260"}}},"links":{"self":"https://api.cars.co.za/fw/public/v3/vehicle/8319023"}},{"type":"vehicle","id":"8319026","attributes":{"agent_coords_0_coord":-25.895796,"agent_coords_1_coord":28.16751,"agent_featured":"2","agent_locality":"Centurion","agent_name":"WeBuyCars Midstream","agent_vin_required":"2","body_type":"Hatchback","body_type_code":"H/B","colour":"White","commercial_type":"a","condition":"As Expected","description":"2017 Opel Corsa 1.0T Ecoflex Essentia 5-Door","finance_available":"1","fuel_type":"Petrol","image":{"version":333390806,"count":8,"path":"carsimages","name":"8319026","extension":".jpg"},"make":"Opel","mileage":"87 000 Km","model":"Corsa","new_or_used":"Used","options":"","price":117900,"province":"Gauteng","reference":"3F8D01131","roadworthy":"1","search_type":"A","seller_type":"agent","title":"2017 Opel Corsa 1.0T EcoFlex Essentia 5-dr","transmission":"Manual","variant":"1.0T EcoFlex Essentia 5-dr","variant_short":"1.0T","vehicle_axle_config":"4X2","website_url":"https://www.cars.co.za/for-sale/used/2017-Opel-Corsa-1.0T-EcoFlex-Essentia-5-dr-Gauteng-Centurion/8319026/","year":2017},"relationships":{"seller":{"data":{"type":"seller","id":"3260"}}},"links":{"self":"https://api.cars.co.za/fw/public/v3/vehicle/8319026"}},{"type":"vehicle","id":"8319033","attributes":{"agent_coords_0_coord":-25.895796,"agent_coords_1_coord":28.16751,"agent_featured":"2","agent_locality":"Centurion","agent_name":"WeBuyCars Midstream","agent_vin_required":"2","body_type":"Sedan","body_type_code":"S/D","colour":"Brown","commercial_type":"a","condition":"Below Average","description":"2010 Mercedes-Benz E Class Sedan E 63 AMG","finance_available":"1","fuel_type":"Petrol","image":{"version":3271172274,"count":8,"path":"carsimages","name":"8319033","extension":".jpg"},"make":"Mercedes-Benz","mileage":"177 000 Km","model":"E-Class","new_or_used":"Used","options":"","price":290900,"province":"Gauteng","reference":"2E9F00677","roadworthy":"1","search_type":"A","seller_type":"agent","title":"2010 Mercedes-Benz E-Class E 63 AMG","transmission":"Automatic","variant":"E 63 AMG","variant_short":"E 63","vehicle_axle_config":"4X2","website_url":"https://www.cars.co.za/for-sale/used/2010-Mercedes-Benz-E-Class-E-63-AMG-Gauteng-Centurion/8319033/","year":2010},"relationships":{"seller":{"data":{"type":"seller","id":"3260"}}},"links":{"self":"https://api.cars.co.za/fw/public/v3/vehicle/8319033"}},{"type":"vehicle","id":"8319034","attributes":{"agent_coords_0_coord":-25.895796,"agent_coords_1_coord":28.16751,"agent_featured":"2","agent_locality":"Centurion","agent_name":"WeBuyCars Midstream","agent_vin_required":"2","body_type":"Sedan","body_type_code":"S/D","colour":"White","commercial_type":"a","condition":"Below Average","description":"2006 Volvo S60 2.5T Auto","finance_available":"1","fuel_type":"Petrol","image":{"version":1122517065,"count":8,"path":"carsimages","name":"8319034","extension":".jpg"},"make":"Volvo","mileage":"187 171 Km","model":"S60","new_or_used":"Used","options":"","price":56900,"province":"Gauteng","reference":"673906904","roadworthy":"1","search_type":"A","seller_type":"agent","title":"2006 Volvo S60 2.5 T Auto","transmission":"Automatic","variant":"2.5 T Auto","variant_short":"2.5 T","vehicle_axle_config":"4X2","website_url":"https://www.cars.co.za/for-sale/used/2006-Volvo-S60-2.5-T-Auto-Gauteng-Centurion/8319034/","year":2006},"relationships":{"seller":{"data":{"type":"seller","id":"3260"}}},"links":{"self":"https://api.cars.co.za/fw/public/v3/vehicle/8319034"}},{"type":"vehicle","id":"8319035","attributes":{"agent_coords_0_coord":-25.895796,"agent_coords_1_coord":28.16751,"agent_featured":"2","agent_locality":"Centurion","agent_name":"WeBuyCars Midstream","agent_vin_required":"2","body_type":"SUV","body_type_code":"SUV","colour":"Silver","commercial_type":"a","condition":"Below Average","description":"2010 Volkswagen Tiguan 1.4 TSI Trend-FUN","finance_available":"1","fuel_type":"Petrol","image":{"version":3688960499,"count":8,"path":"carsimages","name":"8319035","extension":".jpg"},"make":"Volkswagen","mileage":"195 000 Km","model":"Tiguan","new_or_used":"Used","options":"","price":104900,"province":"Gauteng","reference":"EABF00448","roadworthy":"1","search_type":"A","seller_type":"agent","title":"2010 Volkswagen Tiguan 1.4 TSI Trend&Fun","transmission":"Manual","variant":"1.4 TSI Trend&Fun","variant_short":"1.4 TSI","vehicle_axle_config":"4X2","website_url":"https://www.cars.co.za/for-sale/used/2010-Volkswagen-Tiguan-1.4-TSI-TrendFun-Gauteng-Centurion/8319035/","year":2010},"relationships":{"seller":{"data":{"type":"seller","id":"3260"}}},"links":{"self":"https://api.cars.co.za/fw/public/v3/vehicle/8319035"}},{"type":"vehicle","id":"8319038","attributes":{"agent_coords_0_coord":-25.895796,"agent_coords_1_coord":28.16751,"agent_featured":"2","agent_locality":"Centurion","agent_name":"WeBuyCars Midstream","agent_vin_required":"2","body_type":"SUV","body_type_code":"SUV","colour":"Silver","commercial_type":"a","condition":"As Expected","description":"2014 Nissan X Trail 2.0 DCI 4X2 XE (r82/r88)","finance_available":"1","fuel_type":"Diesel","image":{"version":1166378064,"count":8,"path":"carsimages","name":"8319038","extension":".jpg"},"make":"Nissan","mileage":"175 000 Km","model":"X-Trail","new_or_used":"Used","options":"","price":140900,"province":"Gauteng","reference":"0A7804613","roadworthy":"1","search_type":"A","seller_type":"agent","title":"2014 Nissan X-Trail 2.0 dCi 4x2 XE","transmission":"Manual","variant":"2.0 dCi 4x2 XE","variant_short":"2.0 dCi","vehicle_axle_config":"4X2","website_url":"https://www.cars.co.za/for-sale/used/2014-Nissan-X-Trail-2.0-dCi-4x2-XE-Gauteng-Centurion/8319038/","year":2014},"relationships":{"seller":{"data":{"type":"seller","id":"3260"}}},"links":{"self":"https://api.cars.co.za/fw/public/v3/vehicle/8319038"}},{"type":"vehicle","id":"8319039","attributes":{"agent_coords_0_coord":-25.895796,"agent_coords_1_coord":28.16751,"agent_featured":"2","agent_locality":"Centurion","agent_name":"WeBuyCars Midstream","agent_vin_required":"2","body_type":"SUV","body_type_code":"SUV","colour":"White","commercial_type":"a","condition":"As Expected","description":"2017 Opel Mokka / Mokka X 1.4T Enjoy Auto","finance_available":"1","fuel_type":"Petrol","image":{"version":573557164,"count":8,"path":"carsimages","name":"8319039","extension":".jpg"},"make":"Opel","mileage":"110 000 Km","model":"Mokka X","new_or_used":"Used","options":"","price":175900,"province":"Gauteng","reference":"DCDA02747","roadworthy":"1","search_type":"A","seller_type":"agent","title":"2017 Opel Mokka X 1.4T Enjoy Auto","transmission":"Automatic","variant":"1.4T Enjoy Auto","variant_short":"1.4T","vehicle_axle_config":"4X2","website_url":"https://www.cars.co.za/for-sale/used/2017-Opel-Mokka-X-1.4T-Enjoy-Auto-Gauteng-Centurion/8319039/","year":2017},"relationships":{"seller":{"data":{"type":"seller","id":"3260"}}},"links":{"self":"https://api.cars.co.za/fw/public/v3/vehicle/8319039"}},{"type":"vehicle","id":"8319042","attributes":{"agent_coords_0_coord":-25.895796,"agent_coords_1_coord":28.16751,"agent_featured":"2","agent_locality":"Centurion","agent_name":"WeBuyCars Midstream","agent_vin_required":"2","body_type":"Sedan","body_type_code":"S/D","colour":"Silver","commercial_type":"a","condition":"Good","description":"2007 Cadillac BLS 2.8 V6 Auto","finance_available":"1","fuel_type":"Petrol","image":{"version":1278462075,"count":8,"path":"carsimages","name":"8319042","extension":".jpg"},"make":"Cadillac","mileage":"67 529 Km","model":"BLS","new_or_used":"Used","options":"","price":65900,"province":"Gauteng","reference":"938206715","roadworthy":"1","search_type":"A","seller_type":"agent","title":"2007 Cadillac BLS 2.8T V6 Auto","transmission":"Automatic","variant":"2.8T V6 Auto","variant_short":"2.8T","vehicle_axle_config":"4X2","website_url":"https://www.cars.co.za/for-sale/used/2007-Cadillac-BLS-2.8T-V6-Auto-Gauteng-Centurion/8319042/","year":2007},"relationships":{"seller":{"data":{"type":"seller","id":"3260"}}},"links":{"self":"https://api.cars.co.za/fw/public/v3/vehicle/8319042"}},{"type":"vehicle","id":"8319045","attributes":{"agent_coords_0_coord":-25.895796,"agent_coords_1_coord":28.16751,"agent_featured":"2","agent_locality":"Centurion","agent_name":"WeBuyCars Midstream","agent_vin_required":"2","body_type":"SUV","body_type_code":"SUV","colour":"Grey","commercial_type":"a","condition":"Good","description":"2010 Volvo Xc60 3.0T Auto R-Design","finance_available":"1","fuel_type":"Petrol","image":{"version":4039918128,"count":8,"path":"carsimages","name":"8319045","extension":".jpg"},"make":"Volvo","mileage":"188 500 Km","model":"XC60","new_or_used":"Used","options":"","price":85900,"province":"Gauteng","reference":"F12D09809","roadworthy":"1","search_type":"A","seller_type":"agent","title":"2010 Volvo XC60 3.0 T Auto R-Design","transmission":"Automatic","variant":"3.0 T Auto R-Design","variant_short":"3.0 T","vehicle_axle_config":"4X4","website_url":"https://www.cars.co.za/for-sale/used/2010-Volvo-XC60-3.0-T-Auto-R-Design-Gauteng-Centurion/8319045/","year":2010},"relationships":{"seller":{"data":{"type":"seller","id":"3260"}}},"links":{"self":"https://api.cars.co.za/fw/public/v3/vehicle/8319045"}},{"type":"vehicle","id":"8319053","attributes":{"agent_coords_0_coord":-25.895796,"agent_coords_1_coord":28.16751,"agent_featured":"2","agent_locality":"Centurion","agent_name":"WeBuyCars Midstream","agent_vin_required":"2","body_type":"Bus","body_type_code":"B/S","colour":"White","commercial_type":"ab","condition":"Good","description":"2019 Volkswagen T6 Kombi 2.0 Bitdi Trendline Plus DSG (132 KW)","finance_available":"1","fuel_type":"Diesel","image":{"version":131666525,"count":8,"path":"carsimages","name":"8319053","extension":".jpg"},"make":"Volkswagen","mileage":"103 000 Km","model":"Kombi","new_or_used":"Used","options":"","price":585900,"province":"Gauteng","reference":"B67806757","roadworthy":"1","search_type":"A","seller_type":"agent","title":"2019 Volkswagen Kombi T6 2.0 BiTDI Trendline Plus Auto (132kW)","transmission":"Automatic","variant":"T6 2.0 BiTDI Trendline Plus Auto (132kW)","variant_short":"2.0 BiTDI","vehicle_axle_config":"4X2","website_url":"https://www.cars.co.za/for-sale/used/2019-Volkswagen-Kombi-T6-2.0-BiTDI-Trendline-Plus-Auto-132kW-Gauteng-Centurion/8319053/","year":2019},"relationships":{"seller":{"data":{"type":"seller","id":"3260"}}},"links":{"self":"https://api.cars.co.za/fw/public/v3/vehicle/8319053"}},{"type":"vehicle","id":"8319057","attributes":{"agent_coords_0_coord":-25.895796,"agent_coords_1_coord":28.16751,"agent_featured":"2","agent_locality":"Centurion","agent_name":"WeBuyCars Midstream","agent_vin_required":"2","body_type":"Multi Purpose Vehicle","body_type_code":"MPV","colour":"Blue","commercial_type":"a","condition":"Good","description":"2005 Chrysler Grand Voyager 3.3 LX Auto","finance_available":"1","fuel_type":"Petrol","image":{"version":11851332,"count":8,"path":"carsimages","name":"8319057","extension":".jpg"},"make":"Chrysler","mileage":"95 899 Km","model":"Grand Voyager","new_or_used":"Used","options":"","price":75900,"province":"Gauteng","reference":"C69E09710","roadworthy":"1","search_type":"A","seller_type":"agent","title":"2005 Chrysler Grand Voyager 3.3 LX Auto","transmission":"Automatic","variant":"3.3 LX Auto","variant_short":"3.3","vehicle_axle_config":"4X2","website_url":"https://www.cars.co.za/for-sale/used/2005-Chrysler-Grand-Voyager-3.3-LX-Auto-Gauteng-Centurion/8319057/","year":2005},"relationships":{"seller":{"data":{"type":"seller","id":"3260"}}},"links":{"self":"https://api.cars.co.za/fw/public/v3/vehicle/8319057"}},{"type":"vehicle","id":"8319061","attributes":{"agent_coords_0_coord":-25.895796,"agent_coords_1_coord":28.16751,"agent_featured":"2","agent_locality":"Centurion","agent_name":"WeBuyCars Midstream","agent_vin_required":"2","body_type":"Sedan","body_type_code":"S/D","colour":"White","commercial_type":"a","condition":"Below Average","description":"2009 Ford Focus 2.0 SI","finance_available":"1","fuel_type":"Petrol","image":{"version":151165551,"count":8,"path":"carsimages","name":"8319061","extension":".jpg"},"make":"Ford","mileage":"163 255 Km","model":"Focus","new_or_used":"Used","options":"","price":65900,"province":"Gauteng","reference":"49C611929","roadworthy":"1","search_type":"A","seller_type":"agent","title":"2009 Ford Focus 2.0 Si","transmission":"Manual","variant":"2.0 Si","variant_short":"2.0","vehicle_axle_config":"4X2","website_url":"https://www.cars.co.za/for-sale/used/2009-Ford-Focus-2.0-Si-Gauteng-Centurion/8319061/","year":2009},"relationships":{"seller":{"data":{"type":"seller","id":"3260"}}},"links":{"self":"https://api.cars.co.za/fw/public/v3/vehicle/8319061"}},{"type":"vehicle","id":"8319064","attributes":{"agent_coords_0_coord":-25.895796,"agent_coords_1_coord":28.16751,"agent_featured":"2","agent_locality":"Centurion","agent_name":"WeBuyCars Midstream","agent_vin_required":"2","body_type":"Sedan","body_type_code":"S/D","colour":"White","commercial_type":"a","condition":"Below Average","description":"2012 BMW 3 Series 335i Sport Line Auto (F30)","finance_available":"1","fuel_type":"Petrol","image":{"version":4148575748,"count":8,"path":"carsimages","name":"8319064","extension":".jpg"},"make":"BMW","mileage":"201 422 Km","model":"3 Series","new_or_used":"Used","options":"","price":163900,"province":"Gauteng","reference":"395811104","roadworthy":"1","search_type":"A","seller_type":"agent","title":"2012 BMW 3 Series 335i Sport Auto","transmission":"Automatic","variant":"335i Sport Auto","variant_short":"335i","vehicle_axle_config":"4X2","website_url":"https://www.cars.co.za/for-sale/used/2012-BMW-3-Series-335i-Sport-Auto-Gauteng-Centurion/8319064/","year":2012},"relationships":{"seller":{"data":{"type":"seller","id":"3260"}}},"links":{"self":"https://api.cars.co.za/fw/public/v3/vehicle/8319064"}},{"type":"vehicle","id":"8319069","attributes":{"agent_coords_0_coord":-25.895796,"agent_coords_1_coord":28.16751,"agent_featured":"2","agent_locality":"Centurion","agent_name":"WeBuyCars Midstream","agent_vin_required":"2","body_type":"SUV","body_type_code":"SUV","colour":"White","commercial_type":"a","condition":"Below Average","description":"2018 Mahindra XUV 500 2.2d Mhawk (W6) 7 Seat","finance_available":"1","fuel_type":"Diesel","image":{"version":151165551,"count":8,"path":"carsimages","name":"8319069","extension":".jpg"},"make":"Mahindra","mileage":"103 000 Km","model":"XUV 500","new_or_used":"Used","options":"","price":169900,"province":"Gauteng","reference":"6C8110807","roadworthy":"1","search_type":"A","seller_type":"agent","title":"2018 Mahindra XUV 500 2.2D mHawk 7-seat W6","transmission":"Manual","variant":"2.2D mHawk 7-seat W6","variant_short":"2.2D","vehicle_axle_config":"4X2","website_url":"https://www.cars.co.za/for-sale/used/2018-Mahindra-XUV-500-2.2D-mHawk-7-seat-W6-Gauteng-Centurion/8319069/","year":2018},"relationships":{"seller":{"data":{"type":"seller","id":"3260"}}},"links":{"self":"https://api.cars.co.za/fw/public/v3/vehicle/8319069"}},{"type":"vehicle","id":"8319075","attributes":{"agent_coords_0_coord":-25.895796,"agent_coords_1_coord":28.16751,"agent_featured":"2","agent_locality":"Centurion","agent_name":"WeBuyCars Midstream","agent_vin_required":"2","body_type":"Single Cab Bakkie","body_type_code":"S/C","colour":"Grey","commercial_type":"ab","condition":"Below Average","description":"2011 Nissan Navara 2.5 DCI XE K/cab 4x4 Pick Up Single Cab","finance_available":"1","fuel_type":"Diesel","image":{"version":2572828627,"count":7,"path":"carsimages","name":"8319075","extension":".jpg"},"make":"Nissan","mileage":"223 000 Km","model":"Navara","new_or_used":"Used","options":"","price":123900,"province":"Gauteng","reference":"7B3400704","roadworthy":"1","search_type":"B","seller_type":"agent","title":"2011 Nissan Navara 2.5 dCi XE KingCab 4x4 Single-Cab","transmission":"Manual","variant":"2.5 dCi XE KingCab 4x4 Single-Cab","variant_short":"2.5 dCi","vehicle_axle_config":"4X4","website_url":"https://www.cars.co.za/for-sale/used/2011-Nissan-Navara-2.5-dCi-XE-KingCab-4x4-Single-Cab-Gauteng-Centurion/8319075/","year":2011},"relationships":{"seller":{"data":{"type":"seller","id":"3260"}}},"links":{"self":"https://api.cars.co.za/fw/public/v3/vehicle/8319075"}},{"type":"vehicle","id":"8319078","attributes":{"agent_coords_0_coord":-25.895796,"agent_coords_1_coord":28.16751,"agent_featured":"2","agent_locality":"Centurion","agent_name":"WeBuyCars Midstream","agent_vin_required":"2","body_type":"Multi Purpose Vehicle","body_type_code":"MPV","colour":"Silver","commercial_type":"a","condition":"Below Average","description":"2001 Mercedes-Benz A Class A 160 Classic","finance_available":"1","fuel_type":"Petrol","image":{"version":3912289116,"count":8,"path":"carsimages","name":"8319078","extension":".jpg"},"make":"Mercedes-Benz","mileage":"103 000 Km","model":"A-Class","new_or_used":"Used","options":"","price":39900,"province":"Gauteng","reference":"5ECE11607","roadworthy":"1","search_type":"A","seller_type":"agent","title":"2001 Mercedes-Benz A-Class A 160 Classic","transmission":"Manual","variant":"A 160 Classic","variant_short":"A 160","vehicle_axle_config":"4X2","website_url":"https://www.cars.co.za/for-sale/used/2001-Mercedes-Benz-A-Class-A-160-Classic-Gauteng-Centurion/8319078/","year":2001},"relationships":{"seller":{"data":{"type":"seller","id":"3260"}}},"links":{"self":"https://api.cars.co.za/fw/public/v3/vehicle/8319078"}},{"type":"vehicle","id":"8319080","attributes":{"agent_coords_0_coord":-25.895796,"agent_coords_1_coord":28.16751,"agent_featured":"2","agent_locality":"Centurion","agent_name":"WeBuyCars Midstream","agent_vin_required":"2","body_type":"Hatchback","body_type_code":"H/B","colour":"White","commercial_type":"a","condition":"Very Poor","description":"2009 Fiat Palio 1.2 Active 5-Door","finance_available":"1","fuel_type":"Petrol","image":{"version":121547376,"count":8,"path":"carsimages","name":"8319080","extension":".jpg"},"make":"Fiat","mileage":"153 000 Km","model":"Palio","new_or_used":"Used","options":"","price":25900,"province":"Gauteng","reference":"3FA500898","roadworthy":"1","search_type":"A","seller_type":"agent","title":"2009 Fiat Palio 1.2 5-dr Active","transmission":"Manual","variant":"1.2 5-dr Active","variant_short":"1.2","vehicle_axle_config":"4X2","website_url":"https://www.cars.co.za/for-sale/used/2009-Fiat-Palio-1.2-5-dr-Active-Gauteng-Centurion/8319080/","year":2009},"relationships":{"seller":{"data":{"type":"seller","id":"3260"}}},"links":{"self":"https://api.cars.co.za/fw/public/v3/vehicle/8319080"}},{"type":"vehicle","id":"8319085","attributes":{"agent_coords_0_coord":-25.895796,"agent_coords_1_coord":28.16751,"agent_featured":"2","agent_locality":"Centurion","agent_name":"WeBuyCars Midstream","agent_vin_required":"2","body_type":"Double Cab Bakkie","body_type_code":"D/C","colour":"White","commercial_type":"ab","condition":"Very Poor","description":"2007 GWM LDV 2.2 LUX Pick Up Double Cab","finance_available":"1","fuel_type":"Petrol","image":{"version":2807336833,"count":8,"path":"carsimages","name":"8319085","extension":".jpg"},"make":"GWM","mileage":"115 000 Km","model":"Double-Cab","new_or_used":"Used","options":"","price":52900,"province":"Gauteng","reference":"347400745","roadworthy":"1","search_type":"B","seller_type":"agent","title":"2007 GWM Double-Cab 2.2 MPi Lux","transmission":"Manual","variant":"2.2 MPi Lux","variant_short":"2.2","vehicle_axle_config":"4X2","website_url":"https://www.cars.co.za/for-sale/used/2007-GWM-Double-Cab-2.2-MPi-Lux-Gauteng-Centurion/8319085/","year":2007},"relationships":{"seller":{"data":{"type":"seller","id":"3260"}}},"links":{"self":"https://api.cars.co.za/fw/public/v3/vehicle/8319085"}},{"type":"vehicle","id":"8319088","attributes":{"agent_coords_0_coord":-25.895796,"agent_coords_1_coord":28.16751,"agent_featured":"2","agent_locality":"Centurion","agent_name":"WeBuyCars Midstream","agent_vin_required":"2","body_type":"SUV","body_type_code":"SUV","colour":"Gold","commercial_type":"a","condition":"Good","description":"2015 Porsche Cayenne Diesel (E2 II)","finance_available":"1","fuel_type":"Diesel","image":{"version":959453730,"count":8,"path":"carsimages","name":"8319088","extension":".jpg"},"make":"Porsche","mileage":"118 982 Km","model":"Cayenne","new_or_used":"Used","options":"","price":532900,"province":"Gauteng","reference":"40B710050","roadworthy":"1","search_type":"A","seller_type":"agent","title":"2015 Porsche Cayenne Diesel","transmission":"Automatic","variant":"Diesel","variant_short":"Diesel","vehicle_axle_config":"4X4","website_url":"https://www.cars.co.za/for-sale/used/2015-Porsche-Cayenne-Diesel-Gauteng-Centurion/8319088/","year":2015},"relationships":{"seller":{"data":{"type":"seller","id":"3260"}}},"links":{"self":"https://api.cars.co.za/fw/public/v3/vehicle/8319088"}},{"type":"vehicle","id":"8319089","attributes":{"agent_coords_0_coord":-25.895796,"agent_coords_1_coord":28.16751,"agent_featured":"2","agent_locality":"Centurion","agent_name":"WeBuyCars Midstream","agent_vin_required":"2","body_type":"Double Cab Bakkie","body_type_code":"D/C","colour":"White","commercial_type":"ab","condition":"As Expected","description":"2019 Ford Ranger 2.0d Bi-Turbo Wildtrak Auto Pick Up Double Cab","finance_available":"1","fuel_type":"Diesel","image":{"version":2688109464,"count":8,"path":"carsimages","name":"8319089","extension":".jpg"},"make":"Ford","mileage":"77 016 Km","model":"Ranger","new_or_used":"Used","options":"","price":509900,"province":"Gauteng","reference":"D7B210944","roadworthy":"1","search_type":"B","seller_type":"agent","title":"2019 Ford Ranger 2.0D Bi-Turbo Wildtrak Auto Double-Cab","transmission":"Automatic","variant":"2.0D Bi-Turbo Wildtrak Auto Double-Cab","variant_short":"2.0D","vehicle_axle_config":"4X2","website_url":"https://www.cars.co.za/for-sale/used/2019-Ford-Ranger-2.0D-Bi-Turbo-Wildtrak-Auto-Double-Cab-Gauteng-Centurion/8319089/","year":2019},"relationships":{"seller":{"data":{"type":"seller","id":"3260"}}},"links":{"self":"https://api.cars.co.za/fw/public/v3/vehicle/8319089"}}]